django_mercadopago/__init__.py
django_mercadopago/admin.py
django_mercadopago/apps.py
django_mercadopago/fixtures.py
django_mercadopago/forms.py
django_mercadopago/models.py
django_mercadopago/signals.py
django_mercadopago/urls.py
django_mercadopago/views.py
django_mercadopago/migrations/0001_initial.py
django_mercadopago/migrations/0002_auto_20150923_2328.py
django_mercadopago/migrations/0003_payment_status_detail_length.py
django_mercadopago/migrations/0004_preference_owner.py
django_mercadopago/migrations/0005_auto_20151009_1836.py
django_mercadopago/migrations/0006_preference_paid.py
django_mercadopago/migrations/0007_preference_details.py
django_mercadopago/migrations/0008_auto_20151018_2208.py
django_mercadopago/migrations/0009_payment_notification_null.py
django_mercadopago/migrations/0010_notification_processing.py
django_mercadopago/migrations/0011_payment_approved_null.py
django_mercadopago/migrations/0012_untranslated_migrations.py
django_mercadopago/migrations/__init__.py
django_mercadopago_simple-4.1.1.dist-info/DESCRIPTION.rst
django_mercadopago_simple-4.1.1.dist-info/METADATA
django_mercadopago_simple-4.1.1.dist-info/RECORD
django_mercadopago_simple-4.1.1.dist-info/WHEEL
django_mercadopago_simple-4.1.1.dist-info/metadata.json
django_mercadopago_simple-4.1.1.dist-info/top_level.txt
tests/__init__.py
tests/settings.py
tests/test_views.py
