Metadata-Version: 2.0
Name: django-mercadopago-simple
Version: 4.1.1
Summary: MercadoPago integration for django
Home-page: https://gitlab.com/hobarrera/django-mercadopago
Author: Hugo Osvaldo Barrera
Author-email: hbarrera@z47.io
License: ISC
Platform: UNKNOWN
Classifier: Development Status :: 4 - Beta
Classifier: Environment :: Web Environment
Classifier: Framework :: Django
Classifier: Intended Audience :: Developers
Classifier: Programming Language :: Python :: 3
Classifier: Programming Language :: Python :: 3.4
Classifier: Programming Language :: Python :: 3.5
Classifier: Programming Language :: Python :: 3.6
Classifier: Programming Language :: Python :: 3 :: Only
Classifier: Topic :: Internet :: WWW/HTTP
Classifier: Topic :: Software Development :: Libraries :: Python Modules
Requires-Dist: Django (>=1.8.5)
Requires-Dist: mercadopago (>=0.3.4)
Requires-Dist: setuptools-git (>=1.1)
Requires-Dist: setuptools-scm (>=1.8.0)
Requires-Dist: wheel (>=0.26.0)
Provides-Extra: fixtures
Requires-Dist: factory-boy; extra == 'fixtures'
